README.rst
setup.py
symdisk/__init__.py
symdisk/models.py
symdisk.egg-info/PKG-INFO
symdisk.egg-info/SOURCES.txt
symdisk.egg-info/dependency_links.txt
symdisk.egg-info/requires.txt
symdisk.egg-info/top_level.txt